common/__init__.py
common/app_settings.py
common/apps.py
common/context_processors.py
common/csp_config.py
common/mail.py
common/models.py
common/permissions.py
common/utils.py
common/fixtures/aimmo_characters.json
common/fixtures/aimmo_characters2.json
common/fixtures/aimmo_characters3.json
common/helpers/__init__.py
common/helpers/data_migration_loader.py
common/helpers/emails.py
common/helpers/generators.py
common/helpers/organisation.py
common/migrations/0001_initial.py
common/migrations/0002_emailverification.py
common/migrations/0003_aimmocharacter.py
common/migrations/0004_add_aimmocharacters.py
common/migrations/0005_add_worksheets.py
common/migrations/0006_update_aimmo_character_image_path.py
common/migrations/0007_add_pdf_names_to_first_two_worksheets.py
common/migrations/0008_unlock_worksheet_3.py
common/migrations/0009_add_blocked_time_to_teacher_and_student.py
common/migrations/0010_remove_teacher_title.py
common/migrations/0011_student_login_id.py
common/migrations/0012_usersession.py
common/migrations/0013_class_school.py
common/migrations/0014_login_type.py
common/migrations/0015_dailyactivity.py
common/migrations/0016_joinreleasestudent.py
common/migrations/0017_copy_email_to_username.py
common/migrations/0018_update_aimmo_character_image_path.py
common/migrations/0019_aimmocharacter_alt.py
common/migrations/0020_class_is_active_and_null_access_code.py
common/migrations/0021_school_is_active.py
common/migrations/0022_school_cleanup.py
common/migrations/0023_userprofile_aimmo_badges.py
common/migrations/0024_teacher_invited_by.py
common/migrations/0025_schoolteacherinvitation.py
common/migrations/0026_teacher_remove_join_request.py
common/migrations/0027_class_created_by.py
common/migrations/0028_coding_club_downloads.py
common/migrations/0029_dynamicelement.py
common/migrations/0030_add_maintenance_banner.py
common/migrations/0031_improve_admin_panel.py
common/migrations/0032_dailyactivity_level_control_submits.py
cfl_common-8.9.14.dist-info/METADATA
cfl_common-8.9.14.dist-info/WHEEL
cfl_common-8.9.14.dist-info/top_level.txt
cfl_common-8.9.14.dist-info/RECORD
