Metadata-Version: 2.4
Name: cfl-common
Version: 8.9.14
Classifier: Programming Language :: Python :: 3
Classifier: Operating System :: OS Independent
Requires-Dist: asgiref==3.11.0; python_version >= "3.9"
Requires-Dist: certifi==2025.11.12; python_version >= "3.7"
Requires-Dist: cffi==2.0.0; platform_python_implementation != "PyPy"
Requires-Dist: charset-normalizer==3.4.4; python_version >= "3.7"
Requires-Dist: cryptography==44.0.1; python_version >= "3.7" and python_full_version not in "3.9.0, 3.9.1"
Requires-Dist: diff-match-patch==20241021; python_version >= "3.7"
Requires-Dist: django==5.1.15; python_version >= "3.10"
Requires-Dist: django-countries==7.6.1
Requires-Dist: django-csp==3.8
Requires-Dist: django-formtools==2.5.1; python_version >= "3.8"
Requires-Dist: django-import-export==4.2.0; python_version >= "3.9"
Requires-Dist: django-otp==1.6.3; python_version >= "3.7"
Requires-Dist: django-phonenumber-field==8.4.0; python_version >= "3.10"
Requires-Dist: django-pipeline==4.0.0; python_version >= "3.9"
Requires-Dist: django-two-factor-auth==1.17.0; python_version >= "3.8"
Requires-Dist: djangorestframework==3.16.0; python_version >= "3.9"
Requires-Dist: idna==3.11; python_version >= "3.8"
Requires-Dist: libsass==0.23.0; python_version >= "3.8"
Requires-Dist: more-itertools==8.7.0; python_version >= "3.5"
Requires-Dist: numpy==2.4.0; python_version >= "3.11"
Requires-Dist: pandas==2.3.3; python_version >= "3.9"
Requires-Dist: pgeocode==0.4.0; python_version >= "3.8"
Requires-Dist: pycparser==2.23; implementation_name != "PyPy"
Requires-Dist: pyjwt==2.6.0; python_version >= "3.7"
Requires-Dist: pypng==0.20220715.0
Requires-Dist: python-dateutil==2.9.0.post0; python_version >= "2.7" and python_version not in "3.0, 3.1, 3.2"
Requires-Dist: pytz==2025.2
Requires-Dist: qrcode==7.4.2; python_version >= "3.7"
Requires-Dist: requests==2.32.5; python_version >= "3.9"
Requires-Dist: setuptools==80.9.0; python_version >= "3.9"
Requires-Dist: six==1.17.0; python_version >= "2.7" and python_version not in "3.0, 3.1, 3.2"
Requires-Dist: sqlparse==0.5.5; python_version >= "3.8"
Requires-Dist: tablib==3.7.0; python_version >= "3.9"
Requires-Dist: typing-extensions==4.15.0; python_version >= "3.9"
Requires-Dist: tzdata==2025.3; python_version >= "2"
Requires-Dist: urllib3==2.6.3; python_version >= "3.9"
Requires-Dist: wheel==0.45.1; python_version >= "3.8"
Dynamic: classifier
Dynamic: description
Dynamic: requires-dist
